Metadata-Version: 1.0
Name: dtbsgb-distributions
Version: 0.2
Summary: Gaussian and Binomial distributions - Course Udacity
Home-page: UNKNOWN
Author: Sebastian Buitrago
Author-email: sebastian.buitrago@gmail.com
License: UNKNOWN
Platform: UNKNOWN
